liteobj/__init__.py
liteobj/lite.py
liteobj/requirements.txt
liteobj-0.0.7.dist-info/LICENSE
liteobj-0.0.7.dist-info/METADATA
liteobj-0.0.7.dist-info/WHEEL
liteobj-0.0.7.dist-info/entry_points.txt
liteobj-0.0.7.dist-info/top_level.txt
liteobj-0.0.7.dist-info/RECORD
