Metadata-Version: 2.1
Name: liteobj
Version: 0.0.7
Summary: Create lightweight configs for instantiating ML experiments
Home-page: https://github.com/1lint/liteobj
Author: 1lint
Author-email: 105617163+1lint@users.noreply.github.com
License-File: LICENSE
Requires-Dist: fire (>=0.4.0)
Requires-Dist: omegaconf (>=2.2.3)
